propy_alamstein/small_language_model.py
propy_alamstein-0.1.2.dist-info/METADATA
propy_alamstein-0.1.2.dist-info/WHEEL
propy_alamstein-0.1.2.dist-info/top_level.txt
propy_alamstein-0.1.2.dist-info/RECORD
