Metadata-Version: 2.1
Name: propy_alamstein
Version: 0.1.2
Summary: Final Project for Matt Harrison / MetaSnake's 'Professional Python' Course
Requires-Python: >=3.10
Requires-Dist: beautifulsoup4>=4.12.3
Requires-Dist: ipykernel>=6.29.5
Requires-Dist: ipytest>=0.14.2
Requires-Dist: requests>=2.32.3
